lis3dh/__init__.py
lis3dh/lis3dh.py
lis3dh-0.2.data/scripts/run-lis3dh
lis3dh-0.2.dist-info/LICENSE
lis3dh-0.2.dist-info/METADATA
lis3dh-0.2.dist-info/WHEEL
lis3dh-0.2.dist-info/top_level.txt
lis3dh-0.2.dist-info/RECORD
