Metadata-Version: 2.1
Name: lis3dh
Version: 0.2
Summary: Python3 I2C Driver & Application for LIS3DH Accelerometer
Home-page: https://github.com/feyzikesim/lis3dh
Author: Feyzi Kesim
Author-email: feyzikesim@gmail.com
License: UNKNOWN
Platform: UNKNOWN
Classifier: Programming Language :: Python :: 3
Classifier: License :: OSI Approved :: MIT License
Classifier: Operating System :: OS Independent
Requires-Python: >=3.6
